README.txt
dict_compare.py
setup.py
dict_compare.egg-info/PKG-INFO
dict_compare.egg-info/SOURCES.txt
dict_compare.egg-info/dependency_links.txt
dict_compare.egg-info/top_level.txt