Metadata-Version: 1.0
Name: dict_compare
Version: 1.0.2
Summary: A dictionary comparer with decent difference reporting
Home-page: http://protocultura.cl/hg/dict_compare/
Author: Agustin Villena, Marijn Vriens
Author-email: marijn+dictcompare@metronomo.cl
License: BSD
Keywords: dictionary dict compare library testing unittest
Platform: UNKNOWN
Classifier: Development Status :: 5 - Production/Stable
Classifier: Intended Audience :: Developers
Classifier: License :: OSI Approved :: BSD License
Classifier: Programming Language :: Python
Classifier: Topic :: Software Development :: Libraries
Classifier: Topic :: Software Development :: Testing
